<?xml version="1.0" encoding="utf-8"?>
<mosinstall type="menu" version="1.0.0">
	<name>链接 - 内容项目</name>
	<group>Content|Link</group>
	<author>Joomla! Project</author>
	<creationDate>July 2004</creationDate>
	<copyright>(C) 2005 Open Source Matters. All rights reserved.</copyright>
	<license>http://www.gnu.org/copyleft/gpl.html GNU/GPL</license>
	<authorEmail>admin@joomla.org</authorEmail>
	<authorUrl>www.joomla.org</authorUrl>
	<version>1.0.0</version>
	<description>建立一个连到观看全文的、发布中的内容项目链接</description>
	<params>
		<param name="menu_image" type="imagelist" directory="/images/stories" hide_default="1" default="" label="菜单图片" description="一个放在您菜单项目左边或右边的小图示，图片必须位于images/stories/" />
		<param name="unique_itemid" type="radio" default="0" label="唯一的项目ID" description="在连结中使用唯一的Itemid">
			<option value="0">否</option>
			<option value="1">是</option>
		</param>
	</params>
</mosinstall>
